{
  "1": "گفتگو ۾ سختي نه ڪريو",
  "2": "غصي تي ضابطو رکو",
  "3": "ٻين سان چڱائي ڪريو",
  "4": "تڪبر نه ڪريو",
  "5": "ٻين کي انهن جي غلطين تي معاف ڪريو",
  "6": "لوڪن سان نرميءَ سان ڳالهايو",
  "7": "هڪٻئي جو مذاق نه اڏايو",
  "8": "پنهنجي والدين سان بي ادبي وارو لفظ نه چئو",
  "9": "ڪنهن جي انڌي تقليد نه ڪريو",
  "10": "جيڪڏهن قرضدار تنگ دست هجي ته کيس ادائيگي لاءِ وڌيڪ وقت ڏيو",
  "11": "رشوت ۾ ملوث نه ٿيو",
  "12": "واعدو نه ٽوڙيو",
  "13": "انصاف لاءِ مضبوطيءَ سان بيٺو",
  "14": "عورتن کي به وراثت جو حق آهي",
  "15": "يتيم جي حفاظت ڪريو",
  "16": "هڪٻئي جو مال ناحق نه کائو",
  "17": "لوڪن جي وچ ۾ صلح جي ڪوشش ڪريو",
  "18": "بدگماني کان پاسو ڪريو",
  "19": "جاسوسي ۽ غيبت نه ڪريو",
  "20": "پنهنجو مال خيرات ۾ خرچ ڪريو",
  "21": "ضرورت مندن کي ڳولهي انهن جي مدد ڪريو",
  "22": "ضرورت مندن سان مهربانيءَ سان ڳالهايو",
  "23": "پنهنجي مهمانن جي عزت ڪريو",
  "24": "پنهنجي والدين جا فرمانبردار بڻجو",
  "25": "جيڪو چئو ٿا ان تي عمل ڪريو",
  "26": "بدعنواني کان پري رهو",
  "27": "صرف انهن سان وڙهو جيڪي توهان سان وڙهن ٿا",
  "28": "جدوجهد جاري رکو",
  "29": "دين ۾ ڪا به جبر ناهي",
  "30": "حڪمرانن کي انهن جي قابليت مطابق چونڊيو",
  "31": "ٽولي بندي ۾ نه ورهايو",
  "32": "ڪنجوسي نه ڪريو",
  "33": "حسد نه ڪريو",
  "34": "دغابازي جا حامي نه بڻجو",
  "35": "گناهه ۽ زيادتي کان پري رهو",
  "36": "انصاف پسند بڻجو",
  "37": "نشري پدارٿن ۽ شراب کان پاسو ڪريو",
  "38": "جوئا نه کيڏيو",
  "39": "ٻين جي معبودن جي بي عزتي نه ڪريو",
  "40": "کائو ۽ پيئو، پر حد کان وڌيڪ نه",
  "41": "پناهه گھرندڙن جي حفاظت ۽ مدد ڪريو",
  "42": "الله ڏانهن دعوت حڪمت ۽ سٺي نصيحت سان هجڻ گھرجي",
  "43": "جنهن شيءِ جو توهان کي علم ناهي ان جي پويان نه لڳو",
  "44": "بيڪار ڳالهين کان پري رهو",
  "45": "اجازت وٺڻ کانسواءِ ٻين جي گهرن ۾ داخل نه ٿيو",
  "46": "زمين تي عاجزيءَ سان هلو",
  "47": "لوڪن جي وچ ۾ انصاف سان فيصلو ڪريو",
  "48": "هن دنيا مان پنهنجي حصي کي نظرانداز نه ڪريو",
  "49": "نيڪيءَ جو حڪم ڏيو، برائي کان روڪيو",
  "50": "زمين تي آڪڙجي نه هلو",
  "51": "عورتن کي پنهنجي زينت ظاهر نه ڪرڻ گھرجي",
  "52": "الله جي رحمت مان مايوس نه ٿيو",
  "53": "معاملن جو فيصلو مشوري سان ڪريو",
  "54": "سڀني مذهبن جي لوڪن سان انصاف وارو رويو اختيار ڪريو"
}
