{
    "4": "गुस्सा",
    "1": "बुरी नजर के खिलाफ",
    "2": "जादू टोना के खिलाफ",
    "5": "उदासी",
    "30": "गुस्सा दूर करने के लिए",
    "37": "जब कुछ खो जाए",
    "31": "सिर से कठिनाई दूर करने के लिए",
    "20": "बच्चों के होने की कोई उम्मीद नहीं है",
    "19": "एक दोस्त चाहिए",
    "13": "रोजगार के लिए",
    "18": "अकेला",
    "11": "जलन महसूस होना",
    "3": "चिंता",
    "6": "मुश्किल की घड़ी",
    "7": "सही जोड़ीदार मिलने में कठिनाई",
    "8": "भेदभाव",
    "23": "उदास",
    "21": "जब सराहा नहीं जाए",
    "17": "सिर दर्द",
    "16": "निर्वाह में विशालता के लिए",
    "15": "परीक्षा में सफलता के लिए",
    "14": "पति-पत्नी के बीच प्यार के लिए",
    "12": "आज्ञा न मानने वाले बच्चों के लिए",
    "10": "मुश्किलों का सामना करना पड़ रहा है",
    "9": "संदिग्ध",
    "34": "मन में बेचैनी",
    "33": "फैसले लेते समय अल्लाह पर भरोसा रखें",
    "32": "कठोर व्यवहार किये जाने पर",
    "29": "संघर्ष",
    "28": "पेटदर्द",
    "27": "जब आपने पाप किया",
    "25": "माफ़ी मांगने के लिए",
    "24": "डरा हुआ"
}
