{
  "1": {
    "title": "Pagtatambal sa Allah, Ang Pinakamataas (Shirk)"
  },
  "2": "Pagpatay sa tao nang labag sa batas",
  "3": "Pagsasagawa ng mahika (sihr)",
  "4": "Hindi pagsasagawa ng Salah (Pagdarasal)",
  "5": "Hindi pagbabayad ng Zakat",
  "6": "Hindi pag-aayuno sa buwan ng Ramadan nang walang validong dahilan",
  "7": "Hindi pagsasagawa ng Hajj kapag may kakayahan",
  "8": "Pagpapakita ng kawalang-galang sa mga magulang",
  "9": "Pagputol sa ugnayan ng mga kamag-anak",
  "10": "Pakikipagtalik nang hindi kasal (Zina) at pangangalunya",
  "11": "Homosekswalidad",
  "12": "Interes o Tubo (Riba)",
  "13": "Maling pagkonsumo sa ari-arian ng ulila",
  "14": "Pagsisinungaling tungkol sa Allah at sa Kanyang Sugo",
  "15": "Pagtakas mula sa labanan",
  "16": "Ang Pinuno na nagliligaw sa kanyang mga tagasunod, ang malupit at ang mapang-api",
  "17": "Kayabangan, Pagmamataas, Pagiging Mapagmataas, Kahambugan at Kapritso",
  "18": "Pagbibigay ng huwad na saksi",
  "19": "Pag-inom ng alak, Pagsusugal (qimar)",
  "20": "Paninirang-puri sa mga malinis na babae",
  "21": "Maling pagkuha ng mga napanalunan sa digmaan, pondo ng mga Muslim o Zakat",
  "22": "Pagnanakaw",
  "23": "Mga tulisan sa daan na nananakot sa mga naglalakbay",
  "24": "Paggawa ng huwad na sumpa",
  "25": "Pagkuha sa ari-arian ng tao sa pamamagitan ng kabulaanan",
  "26": "Ilegal na kita",
  "27": "Pagkonsumo ng Haram, Panunuhol",
  "28": "Pagpapakamatay",
  "29": "Pagsasabi ng mga Kasinungalingan",
  "30": "Ang hindi tapat na Hukom",
  "31": "Ang Bugaw at ang taong pinahihintulutan ang kanyang asawa na makiapid",
  "32": "Hindi paglilinis ng sarili mula sa lahat ng bakas ng ihi",
  "33": "Pagpapakitang-tao sa mabuting gawa",
  "34": "Pag-aaral ng sagradong kaalaman para sa kapakanan ng mundong ito o pagtatago nito",
  "35": "Pagtataksil sa tiwala",
  "36": "Paalala sa mga pinagbigyan ng kawanggawa tungkol sa iyong tulong sa kanila",
  "37": "Hindi paniniwala sa tadhana",
  "38": "Pakikinig sa mga pribadong pag-uusap ng mga tao",
  "39": "Paglabag sa pangako o panata",
  "40": "Paniniwala sa mga manghuhula at astrologo",
  "41": "Paghihimagsik ng asawang babae laban sa kanyang asawa",
  "42": "Paggawa ng mga estatwa at larawan",
  "43": "Malakas na pag-iyak, pagpunit ng damit, paghampas sa sarili o pagbunot ng buhok kapag may dumating na kapahamakan",
  "44": "Pagtrato sa iba nang hindi makatarungan",
  "45": "Pagpataw ng labis na pasanin at kayabangan laban sa iba",
  "46": "Pagsasakit o pag-alipusta sa mga Muslim, Paghahanap ng pinsala sa mga lingkod ng Allah",
  "47": "Pagsayad ng laylayan ng damit dahil sa kahambugan",
  "48": "Pagkatay ng hayop sa ngalan ng iba maliban sa Ngalan ng Allah",
  "49": "Pakikipagtalo, paghimay sa mga salita ng iba, at pakikipag-away",
  "50": "Pagtitipid o pandaraya sa pagtimbang o pagsukat ng mga paninda",
  "51": "Pakiramdam na ligtas sa pagpaparusa ng Allah",
  "52": {
    "title": "Pagkawala ng pag-asa sa Habag ng Allah at kawalan ng pag-asa",
    "description": "Binanggit din sa konteksto ng pagsisisi at pagpapatawad."
  },
  "53": "Pang-aagaw sa karapatan ng tagapagmana sa pamamagitan ng mga huling habilin",
  "54": "Panlilinlang at masasamang balak",
  "55": "Ang mga kasalanang nagawa ng nagkasala sa oras ng paggawa ay maaaring hindi ituring na malalaking kasalanan batay sa mga sitwasyon",
  "56": "Ang hindi pagpansin sa pagbabawal ng Allah na Makapangyarihan sa lahat at/o ang pagturing dito na pinahihintulutan ay isang kasalanan",
  "57": "Ang pagpapatuloy sa maliit na kasalanan ay maaaring maging malaking kasalanan",
  "58": "Ang isang kasalanan ay maaaring personal sa pagitan ng isang tao at ng Allah, o may kaugnayan sa ibang tao",
  "59": "Ang isang kasalanang ginawa sa publiko ay isang napakaseryosong pagkakasala"
}
