{
    "1": "Көз тийүүгө каршы",
    "2": "Сыйкырга каршы",
    "3": "Тынчсызданган учурда",
    "4": "Ачууланган учурда",
    "5": "Көңүл чөккөн абалдарда",
    "6": "Оор мезгилдерде",
    "7": "Туура жарды табуудагы кыйынчылык үчүн",
    "8": "Басмырлоого каршы",
    "9": "Күмөн санаган учурда",
    "10": "Кыйынчылык-\\nтарга туш болуу",
    "11": "Кызгануу",
    "12": "Тил албаган балдар үчүн",
    "13": "Жумушка орношуу үчүн",
    "14": "Жубайлардын ортосундагы сүйүү үчүн",
    "15": "Сынактарда ийгилик үчүн",
    "16": "Ырыскынын мол\\nболуусу үчүн",
    "17": "Баш оорууган учурда",
    "18": "Жалгыздык",
    "19": "Доско муктажмын",
    "20": "Балалуу болуу үмүтү жок",
    "21": "Эмгегим бааланган жок",
    "23": "Кайгырганда, капаланганда",
    "24": "Корккон учурда",
    "25": "Кечирим сура",
    "26": "Ооруга дары",
    "27": "Күнөө кылдым",
    "28": "Ич ооруганда",
    "29": "Күрөшүү",
    "30": "Ачуудан арылуу үчүн",
    "31": "Баштагы оордукту кетирүү үчүн",
    "32": "Орой мамиле жасалды",
    "33": "Чечим чыгарууда Аллага тобокел кылгыла",
    "34": "Жүрөктөгү тынчсыздыкта",
    "37": "Бир нерсе жоголгондо"
}
